LICENSE.txt
MANIFEST.in
README.md
README.rst
blog-post.md
blog-post.rst
default_settings.yaml
example_settings.yaml
setup.cfg
setup.py
polygot/.DS_Store
polygot/.coverage
polygot/__init__.py
polygot/__version__.py
polygot/authenticate.py
polygot/cl_utils.py
polygot/htmlCleaner.py
polygot/printpdf.py
polygot/setup.cfg
polygot/utKit.py
polygot.egg-info/PKG-INFO
polygot.egg-info/SOURCES.txt
polygot.egg-info/dependency_links.txt
polygot.egg-info/entry_points.txt
polygot.egg-info/not-zip-safe
polygot.egg-info/requires.txt
polygot.egg-info/top_level.txt
polygot/commonutils/__init__.py
polygot/commonutils/getpackagepath.py
polygot/css/.DS_Store
polygot/css/main.css
polygot/css/main.scss
polygot/css/.sass-cache/297a9a1db688d814ac7c92b8df06ebf07a767429/main.scssc
polygot/tests/__init__.py
polygot/tests/test_authenticate.py
polygot/tests/test_htmlCleaner.py
polygot/tests/test_print.py
polygot/tests/input/Localization.html
polygot/tests/input/example_settings.yaml
polygot/tests/output/Cars_original.pdf
polygot/tests/output/Volkswagen.html
polygot/tests/output/Volkswagen.pdf
polygot/tests/output/Volkswagen_original.pdf