Metadata-Version: 1.1
Name: polygot
Version: 0.1
Summary: Using the readability parser API generate clean HTML and PDF documents of articles found on the web
Home-page: https://github.com/thespacedoctor/polygot
Author: David Young
Author-email: davidrobertyoung@gmail.com
License: MIT
Download-URL: https://github.com/thespacedoctor/polygot/archive/v0.1.zip
Keywords: pdf, html, parser
Platform: UNKNOWN
Classifier: Development Status :: 4 - Beta
Classifier: License :: OSI Approved :: MIT License
Classifier: Programming Language :: Python :: 2.7
Classifier: Topic :: Utilities
